[
  {
    "id": 20112,
    "name": "Petsmart",
    "street": "501 N Frank Sottile Blvd",
    "city": "Kingston",
    "state": "New York",
    "accessible": true,
    "unisex": false,
    "directions": "In the back, to the right of the cats up for adoption.",
    "comment": "",
    "latitude": 41.9704655,
    "longitude": -73.9862419,
    "created_at": "2016-02-01T05:43:55.127Z",
    "updated_at": "2016-02-01T05:43:55.127Z",
    "downvote": 0,
    "upvote": 1,
    "country": "US",
    "changing_table": false,
    "edit_id": 20112,
    "approved": true,
    "distance": 2.278418482092791,
    "bearing": "146.252980138602"
  },
  {
    "id": 5205,
    "name": "Chipotle Grill",
    "street": "1217 Ulster Ave",
    "city": "Kingston",
    "state": "NY",
    "accessible": true,
    "unisex": false,
    "directions": "Gendered single stall restroom inside the chipotle.",
    "comment": "",
    "latitude": 41.9647963,
    "longitude": -73.9896775,
    "created_at": "2014-03-15T19:27:33.755Z",
    "updated_at": "2014-03-15T19:27:44.221Z",
    "downvote": 1,
    "upvote": 1,
    "country": "United States",
    "changing_table": false,
    "edit_id": 5205,
    "approved": true,
    "distance": 2.5723229219222,
    "bearing": "155.15963372394"
  },
  {
    "id": 832,
    "name": "Mother Earth's Storehouse",
    "street": "440 Kings Mall Court",
    "city": "Kingston",
    "state": "NY",
    "accessible": false,
    "unisex": true,
    "directions": "Enter mall, look for Mother Earth's Storehouse. There is a sign on the outside of the building - it's on the side with Modell's, to the right of Fashion Bug. \r\r\r\r\r\r\r\rThere are two gender neutral bathrooms in the back of the store, to the right of the deli. ",
    "comment": null,
    "latitude": 41.964896,
    "longitude": -73.988809,
    "created_at": "2014-02-02T20:50:09.220Z",
    "updated_at": "2014-02-02T20:50:09.220Z",
    "downvote": 1,
    "upvote": 0,
    "country": "US",
    "changing_table": false,
    "edit_id": 832,
    "approved": true,
    "distance": 2.58070563646339,
    "bearing": "153.9424942923"
  },
  {
    "id": 64671,
    "name": "1091 Ulster Ave, Kingston, NY 12401, USA",
    "street": "1091 Ulster Ave",
    "city": "Kingston",
    "state": "New York",
    "accessible": true,
    "unisex": true,
    "directions": "",
    "comment": "",
    "latitude": 41.9612507,
    "longitude": -73.9908986,
    "created_at": "2023-02-19T17:47:58.138Z",
    "updated_at": "2023-02-19T17:47:58.231Z",
    "downvote": 0,
    "upvote": 1,
    "country": "US",
    "changing_table": false,
    "edit_id": 64671,
    "approved": true,
    "distance": 2.7870370320879454,
    "bearing": "158.741496031632"
  },
  {
    "id": 20109,
    "name": "Stewarts",
    "street": "Morton Blvd",
    "city": "Kingston",
    "state": "NY",
    "accessible": true,
    "unisex": true,
    "directions": "To the left of the refrigerated case.",
    "comment": "",
    "latitude": 41.959665,
    "longitude": -73.99307499999999,
    "created_at": "2016-02-01T05:21:28.606Z",
    "updated_at": "2016-02-01T05:21:28.606Z",
    "downvote": 0,
    "upvote": 1,
    "country": "US",
    "changing_table": false,
    "edit_id": 20109,
    "approved": true,
    "distance": 2.8645483039786135,
    "bearing": "162.265895073555"
  },
  {
    "id": 43056,
    "name": "Blue Mountain Bistro To Go",
    "street": "948 NY-28",
    "city": "Kingston",
    "state": "New York",
    "accessible": true,
    "unisex": true,
    "directions": "Behind the counter, right when you walk in. ",
    "comment": "One single occupancy, gender neutral bathroom with locks. ",
    "latitude": 41.9832673,
    "longitude": -74.0857836,
    "created_at": "2018-08-18T18:43:40.766Z",
    "updated_at": "2018-08-18T18:43:40.766Z",
    "downvote": 0,
    "upvote": 0,
    "country": "US",
    "changing_table": false,
    "edit_id": 43056,
    "approved": true,
    "distance": 4.258410977504923,
    "bearing": "258.159004223662"
  },
  {
    "id": 29902,
    "name": "Woodstock Day School",
    "street": "1430 Glasco Turnpike",
    "city": "Saugerties ",
    "state": "NY",
    "accessible": true,
    "unisex": true,
    "directions": "Top and bottom floors of the cafe ( big metal building in centre of campus)",
    "comment": "You must be a student or a visitor to enter campus ",
    "latitude": 42.0495599,
    "longitude": -74.0586427,
    "created_at": "2017-02-25T21:41:45.930Z",
    "updated_at": "2017-02-25T21:41:45.930Z",
    "downvote": 0,
    "upvote": 0,
    "country": "US",
    "changing_table": false,
    "edit_id": 29902,
    "approved": true,
    "distance": 4.362720476061628,
    "bearing": "313.258156320272"
  },
  {
    "id": 20115,
    "name": "Stockade Tavern",
    "street": "313 Fair St",
    "city": "Kingston",
    "state": "New York",
    "accessible": false,
    "unisex": true,
    "directions": "There are two gender neutral bathrooms. They are all the way in the back of the establishment; walk past the bar and take a left.",
    "comment": "Restrooms are for bar patrons.",
    "latitude": 41.9347619,
    "longitude": -74.0194921,
    "created_at": "2016-02-01T06:05:53.022Z",
    "updated_at": "2016-02-01T06:05:53.022Z",
    "downvote": 0,
    "upvote": 2,
    "country": "US",
    "changing_table": false,
    "edit_id": 20115,
    "approved": true,
    "distance": 4.560700245861494,
    "bearing": "191.706685604392"
  },
  {
    "id": 43373,
    "name": "Hudson Valley LGBTQ Community Center",
    "street": "300 Wall Street",
    "city": "Kingston ",
    "state": "NY",
    "accessible": true,
    "unisex": true,
    "directions": "First floor on your right when you enter, and also upstairs on the second floor, down the hall on the right. There are stairs or a lift to get to the second floor.",
    "comment": "Open during business hours and also during evening and weekend events.",
    "latitude": 41.9339609,
    "longitude": -74.0194775,
    "created_at": "2018-09-04T03:52:23.035Z",
    "updated_at": "2018-09-04T03:52:23.035Z",
    "downvote": 0,
    "upvote": 1,
    "country": "US",
    "changing_table": true,
    "edit_id": 43373,
    "approved": true,
    "distance": 4.615294178849937,
    "bearing": "191.55638524588"
  },
  {
    "id": 47625,
    "name": "Hudson Valley LGBTQ Community Center",
    "street": "300 Wall Street",
    "city": "Kingston",
    "state": "NY",
    "accessible": false,
    "unisex": true,
    "directions": "One bathroom on first floor, to the right of the entrance. More bathrooms on the second floor at the end of hall (accessible via stairs or wheelchair lift) ",
    "comment": "Mailing Address: Hudson Valley LGBTQ Community Center Inc.PO Box 3994Kingston, New York 12402Phone: 845.331.5300 Hours are 9:30AM-5:00Pm Mon-Fri. Also open late/weekends during special events.",
    "latitude": 41.9339609,
    "longitude": -74.0194775,
    "created_at": "2019-02-19T20:50:39.467Z",
    "updated_at": "2019-03-17T01:25:10.612Z",
    "downvote": 0,
    "upvote": 1,
    "country": "US",
    "changing_table": false,
    "edit_id": 1271,
    "approved": true,
    "distance": 4.615294178849937,
    "bearing": "191.55638524588"
  }
]